bunzbar/__init__.py
bunzbar/config.py
bunzbar/infos.py
bunzbar-0.72.dist-info/LICENSE
bunzbar-0.72.dist-info/METADATA
bunzbar-0.72.dist-info/WHEEL
bunzbar-0.72.dist-info/entry_points.txt
bunzbar-0.72.dist-info/top_level.txt
bunzbar-0.72.dist-info/RECORD
