Metadata-Version: 2.1
Name: bunzbar
Version: 0.72
Summary: Display useful information in status bar. Even stabler that the old 0.71 version.
Author: 02742
Classifier: Programming Language :: Python :: 3
Classifier: License :: OSI Approved :: GNU General Public License v3 (GPLv3)
License-File: LICENSE
Requires-Dist: tsv-calendar
Requires-Dist: psutil
